odoo/addons/l10n_fr_account_vat_return_selenium/README.rst
odoo/addons/l10n_fr_account_vat_return_selenium/__init__.py
odoo/addons/l10n_fr_account_vat_return_selenium/__manifest__.py
odoo/addons/l10n_fr_account_vat_return_selenium/i18n/l10n_fr_account_vat_return_selenium.pot
odoo/addons/l10n_fr_account_vat_return_selenium/models/__init__.py
odoo/addons/l10n_fr_account_vat_return_selenium/models/l10n_fr_account_vat_return.py
odoo/addons/l10n_fr_account_vat_return_selenium/readme/CONTRIBUTORS.rst
odoo/addons/l10n_fr_account_vat_return_selenium/readme/DESCRIPTION.rst
odoo/addons/l10n_fr_account_vat_return_selenium/readme/ROADMAP.rst
odoo/addons/l10n_fr_account_vat_return_selenium/readme/USAGE.rst
odoo/addons/l10n_fr_account_vat_return_selenium/static/description/icon.png
odoo/addons/l10n_fr_account_vat_return_selenium/static/description/index.html
odoo/addons/l10n_fr_account_vat_return_selenium/views/l10n_fr_account_vat_return.xml
odoo14_addon_l10n_fr_account_vat_return_selenium-14.0.1.0.1.dev4.dist-info/METADATA
odoo14_addon_l10n_fr_account_vat_return_selenium-14.0.1.0.1.dev4.dist-info/WHEEL
odoo14_addon_l10n_fr_account_vat_return_selenium-14.0.1.0.1.dev4.dist-info/top_level.txt
odoo14_addon_l10n_fr_account_vat_return_selenium-14.0.1.0.1.dev4.dist-info/RECORD
